person_tracking/Person_face_track.py
person_tracking/cfgs/coco.json
person_tracking/data/coco/labels.txt
person_tracking/fractal/anchors/__init__.py
person_tracking/fractal/anchors/anchors.py
person_tracking/fractal/anchors/anchors_generator.py
person_tracking/fractal/anchors/encoder.py
person_tracking/fractal/anchors/utils.py
person_tracking/fractal/common_utils/__init__.py
person_tracking/fractal/common_utils/img_utils.py
person_tracking/fractal/common_utils/patch_utils.py
person_tracking/fractal/deep_sort/__init__.py
person_tracking/fractal/deep_sort/detection.py
person_tracking/fractal/deep_sort/feature_extractor.py
person_tracking/fractal/deep_sort/iou_matching.py
person_tracking/fractal/deep_sort/kalman_filter.py
person_tracking/fractal/deep_sort/linear_assignment.py
person_tracking/fractal/deep_sort/model.py
person_tracking/fractal/deep_sort/nn_matching.py
person_tracking/fractal/deep_sort/preprocessing.py
person_tracking/fractal/deep_sort/track.py
person_tracking/fractal/deep_sort/tracker.py
person_tracking/fractal/loaders/__init__.py
person_tracking/fractal/loaders/bbox_transforms.py
person_tracking/fractal/loaders/dataloaders.py
person_tracking/fractal/loaders/utils.py
person_tracking/fractal/losses/__init__.py
person_tracking/fractal/losses/get_loss.py
person_tracking/fractal/losses/yolov3_loss.py
person_tracking/fractal/metrics/__init__.py
person_tracking/fractal/metrics/voc_map.py
person_tracking/fractal/nets/__init__.py
person_tracking/fractal/nets/darknet.py
person_tracking/fractal/optims/__init__.py
person_tracking/fractal/optims/get_optims.py
person_tracking/fractal/optims/get_schedulers.py
person_tracking/fractal/superai/.ipynb_checkpoints/img_transforms-checkpoint.py
person_tracking/fractal/superai/.ipynb_checkpoints/loaders-checkpoint.py
person_tracking/fractal/superai/Nets/__init__.py
person_tracking/fractal/superai/Nets/densenet.py
person_tracking/fractal/superai/Nets/inceptionresnetv2.py
person_tracking/fractal/superai/Nets/resnets.py
person_tracking-0.1.9.dist-info/entry_points.txt
person_tracking-0.1.9.dist-info/WHEEL
person_tracking-0.1.9.dist-info/METADATA
person_tracking-0.1.9.dist-info/RECORD
